xtick/__init__.py
xtick-0.0.1.dist-info/LICENSE
xtick-0.0.1.dist-info/METADATA
xtick-0.0.1.dist-info/WHEEL
xtick-0.0.1.dist-info/top_level.txt
xtick-0.0.1.dist-info/RECORD
