Metadata-Version: 2.1
Name: xtick
Version: 0.0.1
Summary: UNKNOWN
Home-page: https://github.com/alpha-xone/xtick
Author: Alpha x1
Author-email: alpha.xone@outlook.com
License: Apache
Platform: UNKNOWN
Classifier: License :: OSI Approved :: Apache Software License
Classifier: Programming Language :: Python :: 3
Classifier: Programming Language :: Python :: 3.6
Requires-Dist: inflection (>=0.3.1)
Requires-Dist: numpy (>=1.15.0)
Requires-Dist: pandas (>=0.23.4)
Requires-Dist: pyarrow (>=0.11.1)
Requires-Dist: python-dateutil (>=2.7.5)
Requires-Dist: pytz (>=2018.7)
Requires-Dist: six (>=1.11.0)
